nvidia-monitor/__init__.py
nvidia_monitor/__init__.py
nvidia_monitor/process.py
nvidia_monitor/queries.py
nvidia_monitor/status.py
nvidia_monitor/test.py
nvidia_monitor-1.1.7.dist-info/LICENSE
nvidia_monitor-1.1.7.dist-info/METADATA
nvidia_monitor-1.1.7.dist-info/WHEEL
nvidia_monitor-1.1.7.dist-info/top_level.txt
nvidia_monitor-1.1.7.dist-info/RECORD
